benchmarks/bench_cross_datastore.py
chdb_ds-0.0.8.dist-info/licenses/LICENSE
datastore/__init__.py
datastore/case_when.py
datastore/column_expr.py
datastore/conditions.py
datastore/config.py
datastore/connection.py
datastore/core.py
datastore/enums.py
datastore/exceptions.py
datastore/executor.py
datastore/expression_evaluator.py
datastore/expressions.py
datastore/function_definitions.py
datastore/function_executor.py
datastore/function_mixin.py
datastore/function_registry.py
datastore/functions.py
datastore/groupby.py
datastore/lazy_ops.py
datastore/lazy_result.py
datastore/pandas_api.py
datastore/pandas_compat.py
datastore/query_planner.py
datastore/schema_state.py
datastore/sql_builder.py
datastore/sql_executor.py
datastore/table_functions.py
datastore/uri_parser.py
datastore/utils.py
datastore/accessors/__init__.py
datastore/accessors/array.py
datastore/accessors/base.py
datastore/accessors/datetime.py
datastore/accessors/geo.py
datastore/accessors/ip.py
datastore/accessors/json.py
datastore/accessors/string.py
datastore/accessors/url.py
datastore/dtype_correction/__init__.py
datastore/dtype_correction/config.py
datastore/dtype_correction/registry.py
datastore/dtype_correction/rules.py
examples/example_explain.py
examples/example_from_uri.py
examples/example_lazy_execution.py
examples/example_mixed_execution.py
examples/example_pandas_compat.py
examples/example_pandas_extended.py
examples/example_pandas_methods.py
examples/example_profiling.py
examples/example_table_functions.py
refs/benchmark_chdb_duckdb_polars.py
refs/benchmark_datastore_vs_pandas.py
refs/benchmark_pandas_vs_sql.py
refs/benchmark_where_approaches.py
refs/kaggle_pandas_compat_test.py
refs/pandas_common_operations.py
refs/simple_bench.py
scripts/check_charset.py
scripts/fetch_ch_functions.py
scripts/fix_suspicious_tests.py
scripts/replace_assert_functions.py
scripts/update_version.py
chdb_ds-0.0.8.dist-info/METADATA
chdb_ds-0.0.8.dist-info/WHEEL
chdb_ds-0.0.8.dist-info/top_level.txt
chdb_ds-0.0.8.dist-info/RECORD
