Metadata-Version: 2.4
Name: chdb-ds
Version: 0.0.8
Summary: A Pandas-like data manipulation framework with automatic SQL generation
Author-email: auxten <auxtenwpc@gmail.com>
License: Apache-2.0
Project-URL: Homepage, https://github.com/auxten/chdb-ds
Project-URL: Documentation, https://github.com/auxten/chdb-ds
Project-URL: Repository, https://github.com/auxten/chdb-ds
Project-URL: Issues, https://github.com/auxten/chdb-ds/issues
Keywords: datastore,pandas,sql,query,builder,database,clickhouse,data manipulation,analytics,dataframe,chdb
Classifier: Development Status :: 3 - Alpha
Classifier: Intended Audience :: Developers
Classifier: License :: OSI Approved :: Apache Software License
Classifier: Programming Language :: Python :: 3
Classifier: Programming Language :: Python :: 3.9
Classifier: Programming Language :: Python :: 3.10
Classifier: Programming Language :: Python :: 3.11
Classifier: Programming Language :: Python :: 3.12
Classifier: Programming Language :: Python :: 3.13
Classifier: Programming Language :: SQL
Classifier: Topic :: Software Development :: Libraries :: Python Modules
Classifier: Topic :: Database
Classifier: Topic :: Scientific/Engineering :: Information Analysis
Classifier: Operating System :: POSIX
Classifier: Operating System :: MacOS :: MacOS X
Classifier: Operating System :: Microsoft :: Windows
Requires-Python: >=3.9
License-File: LICENSE
Requires-Dist: chdb>=4.0.0b6
Requires-Dist: pandas>=2.1.0
Provides-Extra: dev
Requires-Dist: pytest>=7.0.0; extra == "dev"
Requires-Dist: pytest-cov>=4.0.0; extra == "dev"
Requires-Dist: black>=23.0.0; extra == "dev"
Requires-Dist: flake8>=6.0.0; extra == "dev"
Requires-Dist: pre-commit>=3.0.0; extra == "dev"
Dynamic: license-file
